vue_js_reverse/__init__.py
vue_js_reverse/core.py
vue_js_reverse/js_reverse_settings.py
vue_js_reverse/models.py
vue_js_reverse/rjsmin.py
vue_js_reverse/views.py
vue_js_reverse/management/__init__.py
vue_js_reverse/management/commands/__init__.py
vue_js_reverse/management/commands/vue_js_reverse.py
vue_js_reverse/templates/vue_js_reverse/urls_js.tpl
vue_js_reverse/templatetags/__init__.py
vue_js_reverse/templatetags/js_reverse.py
vue_js_reverse/tests/__init__.py
vue_js_reverse/tests/helper.py
vue_js_reverse/tests/settings.py
vue_js_reverse/tests/test_urlconf_urls.py
vue_js_reverse/tests/test_urls.py
vue_js_reverse/tests/unit_tests.py
vue_js_reverse/tests/utils.py
vue_js_reverse-0.0.8.dist-info/AUTHORS
vue_js_reverse-0.0.8.dist-info/LICENSE
vue_js_reverse-0.0.8.dist-info/METADATA
vue_js_reverse-0.0.8.dist-info/WHEEL
vue_js_reverse-0.0.8.dist-info/top_level.txt
vue_js_reverse-0.0.8.dist-info/RECORD
