Metadata-Version: 2.1
Name: vue_js_reverse
Version: 0.0.8
Summary: Vue JS Reverse
Home-page: https://github.com/miklagard/vue-js-reverse
Author: Cem Yildiz
Author-email: cem.yildiz@ya.ru
Classifier: Programming Language :: Python :: 3
Classifier: License :: OSI Approved :: MIT License
Classifier: Operating System :: OS Independent
Requires-Python: >=3.6
License-File: LICENSE
License-File: AUTHORS
